aiobastion/__init__.py
aiobastion/__main__.py
aiobastion/accountgroup.py
aiobastion/accounts.py
aiobastion/aim.py
aiobastion/api_options.py
aiobastion/applications.py
aiobastion/config.py
aiobastion/cyberark.py
aiobastion/exceptions.py
aiobastion/platforms.py
aiobastion/safe.py
aiobastion/session_management.py
aiobastion/system_health.py
aiobastion/users.py
aiobastion/utilities.py
aiobastion-0.1.9.dist-info/licenses/LICENSE
aiobastion-0.1.9.dist-info/METADATA
aiobastion-0.1.9.dist-info/WHEEL
aiobastion-0.1.9.dist-info/top_level.txt
aiobastion-0.1.9.dist-info/RECORD
