Metadata-Version: 2.4
Name: aiobastion
Version: 0.1.9
Summary: Manage your Cyberark implementation
Author-email: Gautier Leveille <gleveille@pm.me>
License: Copyright (c) 2018 The Python Packaging Authority
Project-URL: Homepage, https://github.com/labanquepostale/aiobastion
Project-URL: Bug Reports, https://github.com/labanquepostale/aiobastion/issues
Project-URL: Source, https://github.com/labanquepostale/aiobastion/
Keywords: cyberark
Classifier: Development Status :: 4 - Beta
Classifier: Intended Audience :: Developers
Classifier: Intended Audience :: System Administrators
Classifier: Topic :: System :: Systems Administration
Classifier: Topic :: Utilities
Classifier: License :: OSI Approved :: MIT License
Classifier: Programming Language :: Python :: 3
Classifier: Programming Language :: Python :: 3.7
Classifier: Programming Language :: Python :: 3.8
Classifier: Programming Language :: Python :: 3.9
Classifier: Programming Language :: Python :: 3.10
Classifier: Programming Language :: Python :: 3.11
Classifier: Programming Language :: Python :: 3 :: Only
Requires-Python: >=3.7
License-File: LICENSE
Requires-Dist: pyyaml
Requires-Dist: aiohttp
Provides-Extra: dev
Provides-Extra: test
Requires-Dist: coverage; extra == "test"
Requires-Dist: unittest; extra == "test"
Dynamic: license-file
